sllm_store/_C.cpython-310-x86_64-linux-gnu.so
sllm_store/__init__.py
sllm_store/_checkpoint_store.cpython-310-x86_64-linux-gnu.so
sllm_store/cli.py
sllm_store/client.py
sllm_store/device_map_utils.py
sllm_store/libglog.so
sllm_store/libglog.so.0.6.0
sllm_store/libglog.so.1
sllm_store/logger.py
sllm_store/server.py
sllm_store/torch.py
sllm_store/transformers.py
sllm_store/utils.py
sllm_store/proto/__init__.py
sllm_store/proto/storage_pb2.py
sllm_store/proto/storage_pb2_grpc.py
serverless_llm_store-0.8.0.dist-info/METADATA
serverless_llm_store-0.8.0.dist-info/WHEEL
serverless_llm_store-0.8.0.dist-info/entry_points.txt
serverless_llm_store-0.8.0.dist-info/top_level.txt
serverless_llm_store-0.8.0.dist-info/RECORD
