Metadata-Version: 2.1
Name: serverless-llm-store
Version: 0.8.0
Requires-Dist: accelerate==1.7.0
Requires-Dist: bitsandbytes==0.46.0
Requires-Dist: click==8.1.7
Requires-Dist: grpcio==1.72.1
Requires-Dist: grpcio-tools==1.64.0
Requires-Dist: peft==0.15.2
Requires-Dist: torch==2.7.0
Requires-Dist: transformers==4.52.4
Provides-Extra: test
Requires-Dist: pytest; extra == "test"
Requires-Dist: accelerate>=0.27.2; extra == "test"
Requires-Dist: transformers>=4.37.2; extra == "test"
Requires-Dist: parameterized; extra == "test"
